cdklabs/cdk_ssm_documents/__init__.py
cdklabs/cdk_ssm_documents/py.typed
cdklabs/cdk_ssm_documents/_jsii/__init__.py
cdklabs/cdk_ssm_documents/_jsii/cdk-ssm-documents@0.0.50.jsii.tgz
cdklabs.cdk_ssm_documents-0.0.50.dist-info/LICENSE
cdklabs.cdk_ssm_documents-0.0.50.dist-info/METADATA
cdklabs.cdk_ssm_documents-0.0.50.dist-info/NOTICE
cdklabs.cdk_ssm_documents-0.0.50.dist-info/WHEEL
cdklabs.cdk_ssm_documents-0.0.50.dist-info/top_level.txt
cdklabs.cdk_ssm_documents-0.0.50.dist-info/RECORD
